Metadata-Version: 2.1
Name: qtworker
Version: 1.0.2
Summary: Generic worker for QThreadpools
Author-email: Kolja Wagner <k.wagner@meteo.uni-hannover.de>
Project-URL: Documentation, https://qtworker.readthedocs.io/en/latest/
Project-URL: Repository, https://github.com/kolja-wagner/qtworker
Requires-Python: >=3.9
License-File: LICENSE
Requires-Dist: qtpy>2
Provides-Extra: dev
Requires-Dist: pytest; extra == "dev"
Requires-Dist: pytest-cov; extra == "dev"
Requires-Dist: pytest-qt; extra == "dev"
Provides-Extra: doc
Requires-Dist: sphinx>5.3; extra == "doc"
Requires-Dist: sphinx-qt-documentation; extra == "doc"
Requires-Dist: pydata-sphinx-theme>0.14; extra == "doc"
Requires-Dist: sphinx-copybutton; extra == "doc"
